{
  "name": "Lydia Fleming",
  "age": 42,
  "address": {
    "street": "Jacpi Extension",
    "city": "Dovola",
    "state": "CT",
    "zip": "09566"
  },
  "contact": {
    "phone": "(783) 890-2350",
    "servicePhone": "800346474"
  },
  "birthday": "1998-07-13T17:31:28.387Z",
  "ip": "252.40.18.2",
  "foo": "bar",
  "profile": {
    "about": "Vis rilitemi im gapuah humvew atenowta varifpem umma huprake ugagah bidpanha bekav daele ze hujetro havit ufu. Kaosesas purcaled ofpi gi obmo wowa saf kihhossov pumu koigotir hu zopoije uloimu heg. Woesi doba rubib zeibawe kamuveob mi hoha foz numhu woci wo keasgeh lukuha tenojol.",
    "bio": "Vul ducabi folzis kizfebva jazke so kev doctinuh lo cekuso mir bih ga ebbi pucuupe sobhefno. Ifmi af jukurkeh nupulvi zoder tas suut riebobim ebawukmer gutposfuz jovuzdaw cadledad lazoma winabzu hurocte nenan. Ezipeh molomaso vodutlu oza womigiho une cej maki haz fuboginum ri iwajib. Azegiwu be let ni dad vekuk siidojev dod ihmam cuppisah raweri lud utaflo okijo. Jutensus pigeube ja rafef pivuag jowotug purunuhe gizzo jer kumo zekil icuz ofauni ek. Oswahzos ki mip ho jup awilukwu sor dasu noj peplih gil na."
  },
  "apiKey": "893695e5b0f8e695a3f6de963805616be470d18647335c8ed93fd4bb3a5a8093",
  "currency": {
    "code": "GBP",
    "name": "United Kingdom Pound"
  }
}